LICENSE
MANIFEST.in
README.rst
requirements.txt
setup.py
django_authgroupex/__init__.py
django_authgroupex/auth.py
django_authgroupex/conf.py
django_authgroupex/exceptions.py
django_authgroupex/models.py
django_authgroupex/urls.py
django_authgroupex/views.py
django_authgroupex.egg-info/PKG-INFO
django_authgroupex.egg-info/SOURCES.txt
django_authgroupex.egg-info/dependency_links.txt
django_authgroupex.egg-info/requires.txt
django_authgroupex.egg-info/top_level.txt
django_authgroupex/fake/__init__.py
django_authgroupex/fake/forms.py
django_authgroupex/fake/models.py
django_authgroupex/fake/views.py
django_authgroupex/templates/authgroupex/admin_login.html
django_authgroupex/templates/authgroupex/fake_endpoint_fail.html
django_authgroupex/templates/authgroupex/fake_fill.html
django_authgroupex_dev/__init__.py
django_authgroupex_dev/settings.py
django_authgroupex_dev/urls.py
django_authgroupex_dev/wsgi.py
django_authgroupex_dev/devsite/__init__.py
django_authgroupex_dev/devsite/models.py
django_authgroupex_dev/devsite/views.py
django_authgroupex_dev/devsite/templates/base.html
django_authgroupex_dev/devsite/templates/devsite/home.html