Metadata-Version: 1.1
Name: django-authgroupex
Version: 0.4.1
Summary: An authentication backend for Django based on Polytechnique.org's auth-groupe-x SSO protocol.
Home-page: http://github.com/rbarrois/django-authgroupex
Author: Raphaël Barrois
Author-email: raphael.barrois+djauthgroupex@polytechnique.org
License: BSD
Download-URL: http://pypi.python.org/pypi/django-authgroupex/
Keywords: sso,authentication,django,authgroupex
Platform: UNKNOWN
Classifier: Development Status :: 4 - Beta
Classifier: Framework :: Django
Classifier: Intended Audience :: Developers
Classifier: License :: OSI Approved :: BSD License
Classifier: Topic :: Software Development :: Libraries :: Python Modules
Classifier: Operating System :: OS Independent
Classifier: Programming Language :: Python
